odoo/addons/stock_picking_return_empty_package/README.rst
odoo/addons/stock_picking_return_empty_package/__init__.py
odoo/addons/stock_picking_return_empty_package/__manifest__.py
odoo/addons/stock_picking_return_empty_package/i18n/it.po
odoo/addons/stock_picking_return_empty_package/i18n/stock_picking_return_empty_package.pot
odoo/addons/stock_picking_return_empty_package/models/__init__.py
odoo/addons/stock_picking_return_empty_package/models/stock_picking_type.py
odoo/addons/stock_picking_return_empty_package/readme/CONFIGURE.rst
odoo/addons/stock_picking_return_empty_package/readme/CONTRIBUTORS.rst
odoo/addons/stock_picking_return_empty_package/readme/DESCRIPTION.rst
odoo/addons/stock_picking_return_empty_package/static/description/icon.png
odoo/addons/stock_picking_return_empty_package/static/description/index.html
odoo/addons/stock_picking_return_empty_package/tests/__init__.py
odoo/addons/stock_picking_return_empty_package/tests/test_empty_package_at_picking_return.py
odoo/addons/stock_picking_return_empty_package/views/stock_picking_type.xml
odoo/addons/stock_picking_return_empty_package/wizards/__init__.py
odoo/addons/stock_picking_return_empty_package/wizards/stock_return_picking.py
odoo_addon_stock_picking_return_empty_package-16.0.1.0.0.4.dist-info/METADATA
odoo_addon_stock_picking_return_empty_package-16.0.1.0.0.4.dist-info/WHEEL
odoo_addon_stock_picking_return_empty_package-16.0.1.0.0.4.dist-info/top_level.txt
odoo_addon_stock_picking_return_empty_package-16.0.1.0.0.4.dist-info/RECORD
